[
  {
    "name": "Usiel Sandino Silva Rivera",
    "slug": "usiel-sandino-silva-rivera",
    "url": "https://sistemas.azc.uam.mx/Somos/Personal/d5406736"
  },
  {
    "name": "Alejandra Yumuri Velasco Quiroz",
    "slug": "alejandra-yumuri-velasco-quiroz",
    "url": "https://sistemas.azc.uam.mx/Somos/Personal/d54067cc"
  },
  {
    "name": "Alejandro Mora Vázquez",
    "slug": "alejandro-mora-vazquez",
    "url": "https://sistemas.azc.uam.mx/Somos/Personal/d54064ad"
  },
  {
    "name": "Alejandro Cruz Sandoval",
    "slug": "alejandro-cruz-sandoval",
    "url": "https://sistemas.azc.uam.mx/Somos/Personal/d5405f82"
  },
  {
    "name": "Alfonso Jorge Quevedo Martínez",
    "slug": "alfonso-jorge-quevedo-martinez",
    "url": "https://sistemas.azc.uam.mx/Somos/Personal/d54065bc"
  },
  {
    "name": "Ana Lilia Laureano Cruces",
    "slug": "ana-lilia-laureano-cruces",
    "url": "https://sistemas.azc.uam.mx/Somos/Personal/d5406335"
  },
  {
    "name": "Ángeles Belem Priego Sánchez",
    "slug": "angeles-belem-priego-sanchez",
    "url": "https://sistemas.azc.uam.mx/Somos/Personal/d5406596"
  },
  {
    "name": "Antonio Hernández Muñoz",
    "slug": "antonio-hernandez-munoz",
    "url": "https://sistemas.azc.uam.mx/Somos/Personal/d5406250"
  },
  {
    "name": "Arturo Aguilar Vázquez",
    "slug": "arturo-aguilar-vazquez",
    "url": "https://sistemas.azc.uam.mx/Somos/Personal/d5405e05"
  },
  {
    "name": "Beatriz Merchand Hernandez",
    "slug": "beatriz-merchand-hernandez",
    "url": "https://sistemas.azc.uam.mx/Somos/Personal/d54063f0"
  },
  {
    "name": "Beatriz Adriana González Beltrán",
    "slug": "beatriz-adriana-gonzalez-beltran",
    "url": "https://sistemas.azc.uam.mx/Somos/Personal/d54060b0"
  },
  {
    "name": "César Augusto Real Ramírez",
    "slug": "cesar-augusto-real-ramirez",
    "url": "https://sistemas.azc.uam.mx/Somos/Personal/d5406607"
  },
  {
    "name": "Domingo Rodríguez Benavides",
    "slug": "domingo-rodriguez-benavides",
    "url": "https://sistemas.azc.uam.mx/Somos/Personal/d540669e"
  },
  {
    "name": "Eduardo Luis De la Garza Vizcaya",
    "slug": "eduardo-luis-de-la-garza-vizcaya",
    "url": "https://sistemas.azc.uam.mx/Somos/Personal/d5405fa9"
  },
  {
    "name": "Edwin Montes Orozco",
    "slug": "edwin-montes-orozco",
    "url": "https://sistemas.azc.uam.mx/Somos/Personal/d540643a"
  },
  {
    "name": "Efrén González Gómez",
    "slug": "efren-gonzalez-gomez",
    "url": "https://sistemas.azc.uam.mx/Somos/Personal/d54060fe"
  },
  {
    "name": "Enrique Rébora Togno",
    "slug": "enrique-rebora-togno",
    "url": "https://sistemas.azc.uam.mx/Somos/Personal/d540662d"
  },
  {
    "name": "Enrique Avila Soler",
    "slug": "enrique-avila-soler",
    "url": "https://sistemas.azc.uam.mx/Somos/Personal/d5405ea1"
  },
  {
    "name": "Enrique Rébora Togno",
    "slug": "enrique-rebora-togno",
    "url": "https://sistemas.azc.uam.mx/Somos/Personal/d540662d"
  },
  {
    "name": "Esiquio Martin Gutierrez Armenta",
    "slug": "esiquio-martin-gutierrez-armenta",
    "url": "https://sistemas.azc.uam.mx/Somos/Personal/d540616d"
  },
  {
    "name": "Francisco Cervantes de la Torre",
    "slug": "francisco-cervantes-de-la-torre",
    "url": "https://sistemas.azc.uam.mx/Somos/Personal/d5405f14"
  },
  {
    "name": "Francisco Javier Zaragoza Martínez",
    "slug": "francisco-javier-zaragoza-martinez",
    "url": "https://sistemas.azc.uam.mx/Somos/Personal/d540681b"
  },
  {
    "name": "Gabriela Alejandra Garcia Robledo",
    "slug": "gabriela-alejandra-garcia-robledo",
    "url": "https://sistemas.azc.uam.mx/Somos/Personal/d5406066"
  },
  {
    "name": "Germán Téllez Castillo",
    "slug": "german-tellez-castillo",
    "url": "https://sistemas.azc.uam.mx/Somos/Personal/d540675c"
  },
  {
    "name": "Gueorgi Khatchatourov",
    "slug": "gueorgi-khatchatourov",
    "url": "https://sistemas.azc.uam.mx/Somos/Personal/d54062e8"
  },
  {
    "name": "Héctor Cortés León",
    "slug": "hector-cortes-leon",
    "url": "https://sistemas.azc.uam.mx/Somos/Personal/d5405f5e"
  },
  {
    "name": "Hugo Pablo Leyva",
    "slug": "hugo-pablo-leyva",
    "url": "https://sistemas.azc.uam.mx/Somos/Personal/d54064f9"
  },
  {
    "name": "Irma Fernanda Ardón Pulido",
    "slug": "irma-fernanda-ardon-pulido",
    "url": "https://sistemas.azc.uam.mx/Somos/Personal/d5405e7a"
  },
  {
    "name": "Jaime Rodríguez Díaz",
    "slug": "jaime-rodriguez-diaz",
    "url": "https://sistemas.azc.uam.mx/Somos/Personal/d54066c5"
  },
  {
    "name": "Javier Ramírez Rodríguez",
    "slug": "javier-ramirez-rodriguez",
    "url": "https://sistemas.azc.uam.mx/Somos/Personal/d54065e1"
  },
  {
    "name": "Javier Vázquez Héctor",
    "slug": "javier-vazquez-hector",
    "url": "https://sistemas.azc.uam.mx/Somos/Personal/d54067a6"
  },
  {
    "name": "Jesús Loyo Quijada",
    "slug": "jesus-loyo-quijada",
    "url": "https://sistemas.azc.uam.mx/Somos/Personal/d54063a5"
  },
  {
    "name": "Jesús Isidro González Trejo",
    "slug": "jesus-isidro-gonzalez-trejo",
    "url": "https://sistemas.azc.uam.mx/Somos/Personal/d5406147"
  },
  {
    "name": "Jesús Vicente González Sosa",
    "slug": "jesus-vicente-gonzalez-sosa",
    "url": "https://sistemas.azc.uam.mx/Somos/Personal/d5406122"
  },
  {
    "name": "José Alejandro Reyes Ortiz",
    "slug": "jose-alejandro-reyes-ortiz",
    "url": "https://sistemas.azc.uam.mx/Somos/Personal/d5406653"
  },
  {
    "name": "José Ángel Hernández Rodríguez",
    "slug": "jose-angel-hernandez-rodriguez",
    "url": "https://sistemas.azc.uam.mx/Somos/Personal/d5406276"
  },
  {
    "name": "José Antonio Climent Hernández",
    "slug": "jose-antonio-climent-hernandez",
    "url": "https://sistemas.azc.uam.mx/Somos/Personal/d5405f39"
  },
  {
    "name": "José Luis Pantoja Gallegos",
    "slug": "jose-luis-pantoja-gallegos",
    "url": "https://sistemas.azc.uam.mx/Somos/Personal/d540654a"
  },
  {
    "name": "Josué Padilla Cuevas",
    "slug": "josue-padilla-cuevas",
    "url": "https://sistemas.azc.uam.mx/Somos/Personal/d5406520"
  },
  {
    "name": "Josué Figueroa González",
    "slug": "josue-figueroa-gonzalez",
    "url": "https://sistemas.azc.uam.mx/Somos/Personal/d5405ff3"
  },
  {
    "name": "Juan Villegas Cortez",
    "slug": "juan-villegas-cortez",
    "url": "https://sistemas.azc.uam.mx/Somos/Personal/d54067f3"
  },
  {
    "name": "Juan de la Cruz Mejía Téllez",
    "slug": "juan-de-la-cruz-mejia-tellez",
    "url": "https://sistemas.azc.uam.mx/Somos/Personal/d54063cb"
  },
  {
    "name": "Leonardo Daniel Sánchez Martínez",
    "slug": "leonardo-daniel-sanchez-martinez",
    "url": "https://sistemas.azc.uam.mx/Somos/Personal/d5406711"
  },
  {
    "name": "Lisaura Walkiria Rodríguez Alvarado",
    "slug": "lisaura-walkiria-rodriguez-alvarado",
    "url": "https://sistemas.azc.uam.mx/Somos/Personal/d5406678"
  },
  {
    "name": "Luis Eduardo Urbán Rivero",
    "slug": "luis-eduardo-urban-rivero",
    "url": "https://sistemas.azc.uam.mx/Somos/Personal/d5406781"
  },
  {
    "name": "Luis Fernando Hoyos Reyes",
    "slug": "luis-fernando-hoyos-reyes",
    "url": "https://sistemas.azc.uam.mx/Somos/Personal/d54062c3"
  },
  {
    "name": "Marco Antonio Heredia Velasco",
    "slug": "marco-antonio-heredia-velasco",
    "url": "https://sistemas.azc.uam.mx/Somos/Personal/d5406202"
  },
  {
    "name": "Marco Antonio Gutiérrez Villegas",
    "slug": "marco-antonio-gutierrez-villegas",
    "url": "https://sistemas.azc.uam.mx/Somos/Personal/d5406191"
  },
  {
    "name": "Margarita María de Lourdes Sánchez Guerrero",
    "slug": "margarita-maria-de-lourdes-sanchez-guerrero",
    "url": "https://sistemas.azc.uam.mx/Somos/Personal/d54066eb"
  },
  {
    "name": "María Antonieta Ortega Rodríguez",
    "slug": "maria-antonieta-ortega-rodriguez",
    "url": "https://sistemas.azc.uam.mx/Somos/Personal/d54064d3"
  },
  {
    "name": "María Lizbeth Gallardo López",
    "slug": "maria-lizbeth-gallardo-lopez",
    "url": "https://sistemas.azc.uam.mx/Somos/Personal/d5406040"
  },
  {
    "name": "Mariana Hernández González",
    "slug": "mariana-hernandez-gonzalez",
    "url": "https://sistemas.azc.uam.mx/Somos/Personal/d5406228"
  },
  {
    "name": "Maricela Claudia Bravo Contreras",
    "slug": "maricela-claudia-bravo-contreras",
    "url": "https://sistemas.azc.uam.mx/Somos/Personal/d5405ec7"
  },
  {
    "name": "Mariem Henaine Abed",
    "slug": "mariem-henaine-abed",
    "url": "https://sistemas.azc.uam.mx/Somos/Personal/d54061db"
  },
  {
    "name": "Mario Ulises Larqué Saavedra",
    "slug": "mario-ulises-larque-saavedra",
    "url": "https://sistemas.azc.uam.mx/Somos/Personal/d540630e"
  },
  {
    "name": "Martha Mora Torres",
    "slug": "martha-mora-torres",
    "url": "https://sistemas.azc.uam.mx/Somos/Personal/d5406488"
  },
  {
    "name": "Martha Hanel González",
    "slug": "martha-hanel-gonzalez",
    "url": "https://sistemas.azc.uam.mx/Somos/Personal/d54061b6"
  },
  {
    "name": "Miguel Ángel Mondragón Rubiano",
    "slug": "miguel-angel-mondragon-rubiano",
    "url": "https://sistemas.azc.uam.mx/Somos/Personal/d5406415"
  },
  {
    "name": "Miguel Ángel Abreu Hernández",
    "slug": "miguel-angel-abreu-hernandez",
    "url": "https://sistemas.azc.uam.mx/Somos/Personal/d5405ddc"
  },
  {
    "name": "Miguel Ángel López Ontiveros",
    "slug": "miguel-angel-lopez-ontiveros",
    "url": "https://sistemas.azc.uam.mx/Somos/Personal/d5406380"
  },
  {
    "name": "Nicolás Domínguez Vergara",
    "slug": "nicolas-dominguez-vergara",
    "url": "https://sistemas.azc.uam.mx/Somos/Personal/d5405fce"
  },
  {
    "name": "Oscar Herrera Alcántara",
    "slug": "oscar-herrera-alcantara",
    "url": "https://sistemas.azc.uam.mx/Somos/Personal/d540629c"
  },
  {
    "name": "Rafael López Bracho",
    "slug": "rafael-lopez-bracho",
    "url": "https://sistemas.azc.uam.mx/Somos/Personal/d540635c"
  },
  {
    "name": "Rodrigo Pascual Arellano",
    "slug": "rodrigo-pascual-arellano",
    "url": "https://sistemas.azc.uam.mx/Somos/Personal/d540656f"
  },
  {
    "name": "Rodrigo Alexander Castro Campos",
    "slug": "rodrigo-alexander-castro-campos",
    "url": "https://sistemas.azc.uam.mx/Somos/Personal/d5405eee"
  },
  {
    "name": "Román Anselmo Mora Gutiérrez.",
    "slug": "roman-anselmo-mora-gutierrez",
    "url": "https://sistemas.azc.uam.mx/Somos/Personal/d5406461"
  },
  {
    "name": "Ruslan Gabbasov",
    "slug": "ruslan-gabbasov",
    "url": "https://sistemas.azc.uam.mx/Somos/Personal/d540601a"
  },
  {
    "name": "Sergio Miguel García Carranco",
    "slug": "sergio-miguel-garcia-carranco",
    "url": "https://sistemas.azc.uam.mx/Somos/Personal/d540608a"
  },
  {
    "name": "Silvia Beatriz González Brambila",
    "slug": "silvia-beatriz-gonzalez-brambila",
    "url": "https://sistemas.azc.uam.mx/Somos/Personal/d54060d8"
  },
  {
    "name": "Víctor Manuel Alvear Leyva",
    "slug": "victor-manuel-alvear-leyva",
    "url": "https://sistemas.azc.uam.mx/Somos/Personal/d5405e52"
  },
  {
    "name": "Yadira Zavala Osorio",
    "slug": "yadira-zavala-osorio",
    "url": "https://sistemas.azc.uam.mx/Somos/Personal/d5406840"
  }
]
